{
  "openapi": "3.0.1",
  "info": {
    "title": "LECOMS.API",
    "version": "1.0"
  },
  "paths": {
    "/api/Auth/register": {
      "post": {
        "tags": [
          "Auth"
        ],
        "requestBody": {
          "content": {
            "application/json": {
              "schema": {
                "$ref": "#/components/schemas/UserRegisterDTO"
              }
            },
            "text/json": {
              "schema": {
                "$ref": "#/components/schemas/UserRegisterDTO"
              }
            },
            "application/*+json": {
              "schema": {
                "$ref": "#/components/schemas/UserRegisterDTO"
              }
            }
          }
        },
        "responses": {
          "200": {
            "description": "OK"
          },
          "400": {
            "description": "Bad Request",
            "content": {
              "text/plain": {
                "schema": {
                  "$ref": "#/components/schemas/ProblemDetails"
                }
              },
              "application/json": {
                "schema": {
                  "$ref": "#/components/schemas/ProblemDetails"
                }
              },
              "text/json": {
                "schema": {
                  "$ref": "#/components/schemas/ProblemDetails"
                }
              }
            }
          },
          "401": {
            "description": "Unauthorized",
            "content": {
              "text/plain": {
                "schema": {
                  "$ref": "#/components/schemas/ProblemDetails"
                }
              },
              "application/json": {
                "schema": {
                  "$ref": "#/components/schemas/ProblemDetails"
                }
              },
              "text/json": {
                "schema": {
                  "$ref": "#/components/schemas/ProblemDetails"
                }
              }
            }
          },
          "404": {
            "description": "Not Found",
            "content": {
              "text/plain": {
                "schema": {
                  "$ref": "#/components/schemas/ProblemDetails"
                }
              },
              "application/json": {
                "schema": {
                  "$ref": "#/components/schemas/ProblemDetails"
                }
              },
              "text/json": {
                "schema": {
                  "$ref": "#/components/schemas/ProblemDetails"
                }
              }
            }
          }
        }
      }
    },
    "/api/Auth/confirm-email": {
      "post": {
        "tags": [
          "Auth"
        ],
        "requestBody": {
          "content": {
            "application/json": {
              "schema": {
                "$ref": "#/components/schemas/ConfirmEmailRequest"
              }
            },
            "text/json": {
              "schema": {
                "$ref": "#/components/schemas/ConfirmEmailRequest"
              }
            },
            "application/*+json": {
              "schema": {
                "$ref": "#/components/schemas/ConfirmEmailRequest"
              }
            }
          }
        },
        "responses": {
          "200": {
            "description": "OK"
          },
          "400": {
            "description": "Bad Request",
            "content": {
              "text/plain": {
                "schema": {
                  "$ref": "#/components/schemas/ProblemDetails"
                }
              },
              "application/json": {
                "schema": {
                  "$ref": "#/components/schemas/ProblemDetails"
                }
              },
              "text/json": {
                "schema": {
                  "$ref": "#/components/schemas/ProblemDetails"
                }
              }
            }
          },
          "401": {
            "description": "Unauthorized",
            "content": {
              "text/plain": {
                "schema": {
                  "$ref": "#/components/schemas/ProblemDetails"
                }
              },
              "application/json": {
                "schema": {
                  "$ref": "#/components/schemas/ProblemDetails"
                }
              },
              "text/json": {
                "schema": {
                  "$ref": "#/components/schemas/ProblemDetails"
                }
              }
            }
          },
          "404": {
            "description": "Not Found",
            "content": {
              "text/plain": {
                "schema": {
                  "$ref": "#/components/schemas/ProblemDetails"
                }
              },
              "application/json": {
                "schema": {
                  "$ref": "#/components/schemas/ProblemDetails"
                }
              },
              "text/json": {
                "schema": {
                  "$ref": "#/components/schemas/ProblemDetails"
                }
              }
            }
          }
        }
      },
      "get": {
        "tags": [
          "Auth"
        ],
        "parameters": [
          {
            "name": "email",
            "in": "query",
            "schema": {
              "type": "string"
            }
          },
          {
            "name": "token",
            "in": "query",
            "schema": {
              "type": "string"
            }
          }
        ],
        "responses": {
          "200": {
            "description": "OK"
          },
          "400": {
            "description": "Bad Request",
            "content": {
              "text/plain": {
                "schema": {
                  "$ref": "#/components/schemas/ProblemDetails"
                }
              },
              "application/json": {
                "schema": {
                  "$ref": "#/components/schemas/ProblemDetails"
                }
              },
              "text/json": {
                "schema": {
                  "$ref": "#/components/schemas/ProblemDetails"
                }
              }
            }
          },
          "401": {
            "description": "Unauthorized",
            "content": {
              "text/plain": {
                "schema": {
                  "$ref": "#/components/schemas/ProblemDetails"
                }
              },
              "application/json": {
                "schema": {
                  "$ref": "#/components/schemas/ProblemDetails"
                }
              },
              "text/json": {
                "schema": {
                  "$ref": "#/components/schemas/ProblemDetails"
                }
              }
            }
          },
          "404": {
            "description": "Not Found",
            "content": {
              "text/plain": {
                "schema": {
                  "$ref": "#/components/schemas/ProblemDetails"
                }
              },
              "application/json": {
                "schema": {
                  "$ref": "#/components/schemas/ProblemDetails"
                }
              },
              "text/json": {
                "schema": {
                  "$ref": "#/components/schemas/ProblemDetails"
                }
              }
            }
          }
        }
      }
    },
    "/api/Auth/login": {
      "post": {
        "tags": [
          "Auth"
        ],
        "requestBody": {
          "content": {
            "application/json": {
              "schema": {
                "$ref": "#/components/schemas/LoginRequestDTO"
              }
            },
            "text/json": {
              "schema": {
                "$ref": "#/components/schemas/LoginRequestDTO"
              }
            },
            "application/*+json": {
              "schema": {
                "$ref": "#/components/schemas/LoginRequestDTO"
              }
            }
          }
        },
        "responses": {
          "200": {
            "description": "OK"
          },
          "400": {
            "description": "Bad Request",
            "content": {
              "text/plain": {
                "schema": {
                  "$ref": "#/components/schemas/ProblemDetails"
                }
              },
              "application/json": {
                "schema": {
                  "$ref": "#/components/schemas/ProblemDetails"
                }
              },
              "text/json": {
                "schema": {
                  "$ref": "#/components/schemas/ProblemDetails"
                }
              }
            }
          },
          "401": {
            "description": "Unauthorized",
            "content": {
              "text/plain": {
                "schema": {
                  "$ref": "#/components/schemas/ProblemDetails"
                }
              },
              "application/json": {
                "schema": {
                  "$ref": "#/components/schemas/ProblemDetails"
                }
              },
              "text/json": {
                "schema": {
                  "$ref": "#/components/schemas/ProblemDetails"
                }
              }
            }
          },
          "404": {
            "description": "Not Found",
            "content": {
              "text/plain": {
                "schema": {
                  "$ref": "#/components/schemas/ProblemDetails"
                }
              },
              "application/json": {
                "schema": {
                  "$ref": "#/components/schemas/ProblemDetails"
                }
              },
              "text/json": {
                "schema": {
                  "$ref": "#/components/schemas/ProblemDetails"
                }
              }
            }
          }
        }
      }
    },
    "/api/Auth/refresh-token": {
      "post": {
        "tags": [
          "Auth"
        ],
        "requestBody": {
          "content": {
            "application/json": {
              "schema": {
                "$ref": "#/components/schemas/RefreshTokenRequestDTO"
              }
            },
            "text/json": {
              "schema": {
                "$ref": "#/components/schemas/RefreshTokenRequestDTO"
              }
            },
            "application/*+json": {
              "schema": {
                "$ref": "#/components/schemas/RefreshTokenRequestDTO"
              }
            }
          }
        },
        "responses": {
          "200": {
            "description": "OK"
          },
          "400": {
            "description": "Bad Request",
            "content": {
              "text/plain": {
                "schema": {
                  "$ref": "#/components/schemas/ProblemDetails"
                }
              },
              "application/json": {
                "schema": {
                  "$ref": "#/components/schemas/ProblemDetails"
                }
              },
              "text/json": {
                "schema": {
                  "$ref": "#/components/schemas/ProblemDetails"
                }
              }
            }
          },
          "401": {
            "description": "Unauthorized",
            "content": {
              "text/plain": {
                "schema": {
                  "$ref": "#/components/schemas/ProblemDetails"
                }
              },
              "application/json": {
                "schema": {
                  "$ref": "#/components/schemas/ProblemDetails"
                }
              },
              "text/json": {
                "schema": {
                  "$ref": "#/components/schemas/ProblemDetails"
                }
              }
            }
          },
          "404": {
            "description": "Not Found",
            "content": {
              "text/plain": {
                "schema": {
                  "$ref": "#/components/schemas/ProblemDetails"
                }
              },
              "application/json": {
                "schema": {
                  "$ref": "#/components/schemas/ProblemDetails"
                }
              },
              "text/json": {
                "schema": {
                  "$ref": "#/components/schemas/ProblemDetails"
                }
              }
            }
          }
        }
      }
    },
    "/api/Auth/forget-password": {
      "post": {
        "tags": [
          "Auth"
        ],
        "requestBody": {
          "content": {
            "application/json": {
              "schema": {
                "$ref": "#/components/schemas/ForgetPasswordRequestDTO"
              }
            },
            "text/json": {
              "schema": {
                "$ref": "#/components/schemas/ForgetPasswordRequestDTO"
              }
            },
            "application/*+json": {
              "schema": {
                "$ref": "#/components/schemas/ForgetPasswordRequestDTO"
              }
            }
          }
        },
        "responses": {
          "200": {
            "description": "OK"
          },
          "400": {
            "description": "Bad Request",
            "content": {
              "text/plain": {
                "schema": {
                  "$ref": "#/components/schemas/ProblemDetails"
                }
              },
              "application/json": {
                "schema": {
                  "$ref": "#/components/schemas/ProblemDetails"
                }
              },
              "text/json": {
                "schema": {
                  "$ref": "#/components/schemas/ProblemDetails"
                }
              }
            }
          },
          "401": {
            "description": "Unauthorized",
            "content": {
              "text/plain": {
                "schema": {
                  "$ref": "#/components/schemas/ProblemDetails"
                }
              },
              "application/json": {
                "schema": {
                  "$ref": "#/components/schemas/ProblemDetails"
                }
              },
              "text/json": {
                "schema": {
                  "$ref": "#/components/schemas/ProblemDetails"
                }
              }
            }
          },
          "404": {
            "description": "Not Found",
            "content": {
              "text/plain": {
                "schema": {
                  "$ref": "#/components/schemas/ProblemDetails"
                }
              },
              "application/json": {
                "schema": {
                  "$ref": "#/components/schemas/ProblemDetails"
                }
              },
              "text/json": {
                "schema": {
                  "$ref": "#/components/schemas/ProblemDetails"
                }
              }
            }
          }
        }
      }
    },
    "/api/Auth/reset-password": {
      "post": {
        "tags": [
          "Auth"
        ],
        "requestBody": {
          "content": {
            "application/json": {
              "schema": {
                "$ref": "#/components/schemas/ResetPasswordDTO"
              }
            },
            "text/json": {
              "schema": {
                "$ref": "#/components/schemas/ResetPasswordDTO"
              }
            },
            "application/*+json": {
              "schema": {
                "$ref": "#/components/schemas/ResetPasswordDTO"
              }
            }
          }
        },
        "responses": {
          "200": {
            "description": "OK"
          },
          "400": {
            "description": "Bad Request",
            "content": {
              "text/plain": {
                "schema": {
                  "$ref": "#/components/schemas/ProblemDetails"
                }
              },
              "application/json": {
                "schema": {
                  "$ref": "#/components/schemas/ProblemDetails"
                }
              },
              "text/json": {
                "schema": {
                  "$ref": "#/components/schemas/ProblemDetails"
                }
              }
            }
          },
          "401": {
            "description": "Unauthorized",
            "content": {
              "text/plain": {
                "schema": {
                  "$ref": "#/components/schemas/ProblemDetails"
                }
              },
              "application/json": {
                "schema": {
                  "$ref": "#/components/schemas/ProblemDetails"
                }
              },
              "text/json": {
                "schema": {
                  "$ref": "#/components/schemas/ProblemDetails"
                }
              }
            }
          },
          "404": {
            "description": "Not Found",
            "content": {
              "text/plain": {
                "schema": {
                  "$ref": "#/components/schemas/ProblemDetails"
                }
              },
              "application/json": {
                "schema": {
                  "$ref": "#/components/schemas/ProblemDetails"
                }
              },
              "text/json": {
                "schema": {
                  "$ref": "#/components/schemas/ProblemDetails"
                }
              }
            }
          }
        }
      }
    },
    "/api/Email": {
      "post": {
        "tags": [
          "Email"
        ],
        "summary": "Send email",
        "requestBody": {
          "description": "",
          "content": {
            "application/json": {
              "schema": {
                "$ref": "#/components/schemas/EmailRequestDTO"
              }
            },
            "text/json": {
              "schema": {
                "$ref": "#/components/schemas/EmailRequestDTO"
              }
            },
            "application/*+json": {
              "schema": {
                "$ref": "#/components/schemas/EmailRequestDTO"
              }
            }
          }
        },
        "responses": {
          "200": {
            "description": "OK",
            "content": {
              "text/plain": {
                "schema": {
                  "$ref": "#/components/schemas/APIResponse"
                }
              },
              "application/json": {
                "schema": {
                  "$ref": "#/components/schemas/APIResponse"
                }
              },
              "text/json": {
                "schema": {
                  "$ref": "#/components/schemas/APIResponse"
                }
              }
            }
          },
          "400": {
            "description": "Bad Request",
            "content": {
              "text/plain": {
                "schema": {
                  "$ref": "#/components/schemas/ProblemDetails"
                }
              },
              "application/json": {
                "schema": {
                  "$ref": "#/components/schemas/ProblemDetails"
                }
              },
              "text/json": {
                "schema": {
                  "$ref": "#/components/schemas/ProblemDetails"
                }
              }
            }
          }
        }
      }
    },
    "/api/user/profile": {
      "get": {
        "tags": [
          "User"
        ],
        "responses": {
          "200": {
            "description": "OK"
          }
        }
      },
      "put": {
        "tags": [
          "User"
        ],
        "requestBody": {
          "content": {
            "application/json": {
              "schema": {
                "$ref": "#/components/schemas/UserProfileDTO"
              }
            },
            "text/json": {
              "schema": {
                "$ref": "#/components/schemas/UserProfileDTO"
              }
            },
            "application/*+json": {
              "schema": {
                "$ref": "#/components/schemas/UserProfileDTO"
              }
            }
          }
        },
        "responses": {
          "200": {
            "description": "OK"
          }
        }
      }
    },
    "/api/user/change-password": {
      "post": {
        "tags": [
          "User"
        ],
        "requestBody": {
          "content": {
            "application/json": {
              "schema": {
                "$ref": "#/components/schemas/ChangePasswordDTO"
              }
            },
            "text/json": {
              "schema": {
                "$ref": "#/components/schemas/ChangePasswordDTO"
              }
            },
            "application/*+json": {
              "schema": {
                "$ref": "#/components/schemas/ChangePasswordDTO"
              }
            }
          }
        },
        "responses": {
          "200": {
            "description": "OK"
          }
        }
      }
    }
  },
  "components": {
    "schemas": {
      "APIResponse": {
        "type": "object",
        "properties": {
          "statusCode": {
            "$ref": "#/components/schemas/HttpStatusCode"
          },
          "isSuccess": {
            "type": "boolean"
          },
          "errorMessages": {
            "type": "array",
            "items": {
              "type": "string"
            },
            "nullable": true
          },
          "result": {
            "nullable": true
          }
        },
        "additionalProperties": false
      },
      "ChangePasswordDTO": {
        "type": "object",
        "properties": {
          "oldPassword": {
            "type": "string",
            "nullable": true
          },
          "newPassword": {
            "type": "string",
            "nullable": true
          }
        },
        "additionalProperties": false
      },
      "ConfirmEmailRequest": {
        "type": "object",
        "properties": {
          "email": {
            "type": "string",
            "nullable": true
          },
          "token": {
            "type": "string",
            "nullable": true
          }
        },
        "additionalProperties": false
      },
      "EmailRequestDTO": {
        "type": "object",
        "properties": {
          "toEmail": {
            "type": "string",
            "nullable": true
          },
          "subject": {
            "type": "string",
            "nullable": true
          },
          "body": {
            "type": "string",
            "nullable": true
          }
        },
        "additionalProperties": false
      },
      "ForgetPasswordRequestDTO": {
        "type": "object",
        "properties": {
          "email": {
            "type": "string",
            "nullable": true
          }
        },
        "additionalProperties": false
      },
      "HttpStatusCode": {
        "enum": [
          "Continue",
          "SwitchingProtocols",
          "Processing",
          "EarlyHints",
          "OK",
          "Created",
          "Accepted",
          "NonAuthoritativeInformation",
          "NoContent",
          "ResetContent",
          "PartialContent",
          "MultiStatus",
          "AlreadyReported",
          "IMUsed",
          "MultipleChoices",
          "MovedPermanently",
          "Found",
          "SeeOther",
          "NotModified",
          "UseProxy",
          "Unused",
          "TemporaryRedirect",
          "PermanentRedirect",
          "BadRequest",
          "Unauthorized",
          "PaymentRequired",
          "Forbidden",
          "NotFound",
          "MethodNotAllowed",
          "NotAcceptable",
          "ProxyAuthenticationRequired",
          "RequestTimeout",
          "Conflict",
          "Gone",
          "LengthRequired",
          "PreconditionFailed",
          "RequestEntityTooLarge",
          "RequestUriTooLong",
          "UnsupportedMediaType",
          "RequestedRangeNotSatisfiable",
          "ExpectationFailed",
          "MisdirectedRequest",
          "UnprocessableEntity",
          "Locked",
          "FailedDependency",
          "UpgradeRequired",
          "PreconditionRequired",
          "TooManyRequests",
          "RequestHeaderFieldsTooLarge",
          "UnavailableForLegalReasons",
          "InternalServerError",
          "NotImplemented",
          "BadGateway",
          "ServiceUnavailable",
          "GatewayTimeout",
          "HttpVersionNotSupported",
          "VariantAlsoNegotiates",
          "InsufficientStorage",
          "LoopDetected",
          "NotExtended",
          "NetworkAuthenticationRequired"
        ],
        "type": "string"
      },
      "LoginRequestDTO": {
        "type": "object",
        "properties": {
          "username": {
            "type": "string",
            "nullable": true
          },
          "password": {
            "type": "string",
            "nullable": true
          }
        },
        "additionalProperties": false
      },
      "ProblemDetails": {
        "type": "object",
        "properties": {
          "type": {
            "type": "string",
            "nullable": true
          },
          "title": {
            "type": "string",
            "nullable": true
          },
          "status": {
            "type": "integer",
            "format": "int32",
            "nullable": true
          },
          "detail": {
            "type": "string",
            "nullable": true
          },
          "instance": {
            "type": "string",
            "nullable": true
          }
        },
        "additionalProperties": { }
      },
      "RefreshTokenRequestDTO": {
        "type": "object",
        "properties": {
          "refreshToken": {
            "type": "string",
            "nullable": true
          }
        },
        "additionalProperties": false
      },
      "ResetPasswordDTO": {
        "required": [
          "email",
          "newPassword"
        ],
        "type": "object",
        "properties": {
          "email": {
            "minLength": 1,
            "type": "string",
            "format": "email"
          },
          "token": {
            "type": "string",
            "nullable": true
          },
          "newPassword": {
            "minLength": 1,
            "pattern": "^(?=.*[a-z])(?=.*[A-Z])(?=.*\\d)(?=.*[\\W_]).{6,}$",
            "type": "string",
            "format": "password"
          }
        },
        "additionalProperties": false
      },
      "UserProfileDTO": {
        "type": "object",
        "properties": {
          "id": {
            "type": "string",
            "nullable": true
          },
          "userName": {
            "type": "string",
            "nullable": true
          },
          "fullName": {
            "type": "string",
            "nullable": true
          },
          "phoneNumber": {
            "type": "string",
            "nullable": true
          },
          "address": {
            "type": "string",
            "nullable": true
          },
          "dateOfBirth": {
            "type": "string",
            "format": "date-time",
            "nullable": true
          },
          "imageUrl": {
            "type": "string",
            "nullable": true
          }
        },
        "additionalProperties": false
      },
      "UserRegisterDTO": {
        "type": "object",
        "properties": {
          "fullName": {
            "type": "string",
            "nullable": true
          },
          "userName": {
            "type": "string",
            "nullable": true
          },
          "email": {
            "type": "string",
            "nullable": true
          },
          "phoneNumber": {
            "type": "string",
            "nullable": true
          },
          "address": {
            "type": "string",
            "nullable": true
          },
          "dateOfBirth": {
            "type": "string",
            "format": "date-time"
          },
          "password": {
            "type": "string",
            "nullable": true
          }
        },
        "additionalProperties": false
      }
    },
    "securitySchemes": {
      "Bearer": {
        "type": "http",
        "description": "Enter 'Bearer' [space] and then your token.",
        "scheme": "Bearer",
        "bearerFormat": "JWT"
      }
    }
  },
  "security": [
    {
      "Bearer": [ ]
    }
  ]
}